envargparse.py
envargparse-1.0.0.dist-info/LICENSE.txt
envargparse-1.0.0.dist-info/METADATA
envargparse-1.0.0.dist-info/WHEEL
envargparse-1.0.0.dist-info/top_level.txt
envargparse-1.0.0.dist-info/RECORD
