Metadata-Version: 2.1
Name: envargparse
Version: 1.0.0
Summary: Argparse with environment variables
Home-page: https://github.com/orbisvicis/envargparse
Author: Yclept Nemo
Author-email: orbisvicis@gmail.com
License: GPLv3+
Platform: UNKNOWN
Classifier: Development Status :: 5 - Production/Stable
Classifier: Intended Audience :: Developers
Classifier: License :: OSI Approved :: GNU General Public License v3 or later (GPLv3+)
Classifier: Operating System :: OS Independent
Classifier: Programming Language :: Python :: 3 :: Only
Classifier: Topic :: Software Development :: Libraries
Requires-Python: >= 3.7
Requires-Dist: decorator
